easy_unet/__init__.py
easy_unet/module.py
easy_unet-1.0.2.dist-info/licenses/LICENSE
easy_unet-1.0.2.dist-info/METADATA
easy_unet-1.0.2.dist-info/WHEEL
easy_unet-1.0.2.dist-info/top_level.txt
easy_unet-1.0.2.dist-info/RECORD
