Metadata-Version: 2.4
Name: easy-unet
Version: 1.0.2
Summary: A lightweight and flexible PyTorch library providing a modular UNet implementation with advanced attention and normalization blocks for fast image processing and deep learning development.
Author-email: Mehran Bazrafkan <mhrn.bzrafkn.dev@gmail.com>
License-Expression: MIT
Keywords: UNet,PyTorch,deep learning,image segmentation,attention,normalization,machine learning,computer vision
Classifier: Programming Language :: Python :: 3
Classifier: Operating System :: OS Independent
Classifier: Topic :: Scientific/Engineering :: Artificial Intelligence
Classifier: Intended Audience :: Developers
Requires-Python: >=3.10
License-File: LICENSE
Requires-Dist: torch>=1.13
Requires-Dist: einops
Requires-Dist: numpy
Dynamic: license-file
